validpy/Valid.py
validpy/__init__.py
validpy-0.0.3.dist-info/LICENCE.txt
validpy-0.0.3.dist-info/LICENSE
validpy-0.0.3.dist-info/METADATA
validpy-0.0.3.dist-info/WHEEL
validpy-0.0.3.dist-info/top_level.txt
validpy-0.0.3.dist-info/RECORD
