Metadata-Version: 2.1
Name: validpy
Version: 0.0.3
Summary: A simple validation library
Home-page: https://github.com/TeganHakim/validpy
Author: Tegan Hakim
Author-email: tegan.hakim@gmail.com
License: MIT
Platform: UNKNOWN
Classifier: Programming Language :: Python :: 3
Classifier: Programming Language :: Python :: 3.5
Classifier: Programming Language :: Python :: 3.6
Classifier: Programming Language :: Python :: 3.7
Classifier: Programming Language :: Python :: 3.8
Classifier: Programming Language :: Python :: 3.9
Classifier: License :: OSI Approved :: MIT License
Classifier: Operating System :: OS Independent
Requires-Python: >=3.6
